pytest_neo.py
pytest_neo-0.2.5.dist-info/LICENSE
pytest_neo-0.2.5.dist-info/METADATA
pytest_neo-0.2.5.dist-info/WHEEL
pytest_neo-0.2.5.dist-info/entry_points.txt
pytest_neo-0.2.5.dist-info/top_level.txt
pytest_neo-0.2.5.dist-info/RECORD
