Metadata-Version: 2.1
Name: pytest-neo
Version: 0.2.5
Summary: pytest-neo is a plugin for pytest that shows tests like screen of Matrix.
Home-page: UNKNOWN
Author: Ilya Chistyakov
Author-email: ilchistyakov@gmail.com
License: MIT
Project-URL: Source, https://github.com/MyGodIsHe/pytest-neo
Platform: any
Classifier: Development Status :: 3 - Alpha
Classifier: Intended Audience :: Developers
Classifier: License :: OSI Approved :: BSD License
Classifier: Operating System :: POSIX
Classifier: Operating System :: MacOS :: MacOS X
Classifier: Topic :: Software Development :: Testing
Classifier: Topic :: Software Development :: Libraries
Classifier: Topic :: Utilities
Classifier: Programming Language :: Python :: 3
Classifier: Programming Language :: Python :: 3.6
Classifier: Programming Language :: Python :: 3.7
Classifier: Programming Language :: Python :: 3.8
Classifier: Programming Language :: Python :: 3.9
Classifier: Programming Language :: Python :: 3.10
Classifier: Programming Language :: Python :: Implementation :: PyPy
License-File: LICENSE
Requires-Dist: pytest (>=6.2.0)
